sytd/__init__.py
sytd/__main__.py
sytd/web/RobotoMono-Medium.ttf
sytd/web/favicon.ico
sytd/web/main.html
sytd/web/css/bootstrap.bundle.min.js
sytd/web/css/bootstrap.bundle.min.js.map
sytd/web/css/bootstrap.min.css
sytd/web/css/bootstrap.min.css.map
sytd/web/css/custom.css
sytd/web/img/download.svg
sytd/web/img/github.svg
sytd/web/img/globe.svg
sytd/web/img/noinput.svg
sytd/web/js/bootstrap.bundle.min.js
sytd/web/js/bootstrap.bundle.min.js.map
sytd/web/js/script.js
sytd-1.0.10.dist-info/LICENSE
sytd-1.0.10.dist-info/METADATA
sytd-1.0.10.dist-info/WHEEL
sytd-1.0.10.dist-info/entry_points.txt
sytd-1.0.10.dist-info/top_level.txt
sytd-1.0.10.dist-info/RECORD
