Metadata-Version: 2.1
Name: sytd
Version: 1.0.10
Summary: Simple YouTube Downloader
Home-page: https://github.com/tomg404/Simple-YouTube-Downloader
Author: Tom Gaimann
Author-email: tom.gaimann@outlook.com
License: MIT
Keywords: gui,downloader,youtube,simple
Platform: UNKNOWN
Classifier: Development Status :: 4 - Beta
Classifier: License :: OSI Approved :: MIT License
Classifier: Programming Language :: Python :: 3
Classifier: Operating System :: Microsoft :: Windows
Classifier: Operating System :: POSIX :: Linux
Requires-Python: >=3.5
Requires-Dist: Eel (==0.11.0)
Requires-Dist: bottle (==0.12.18)
Requires-Dist: gevent (==1.5.0)
Requires-Dist: youtube-dl (==2020.3.24)
